mathsimplicity/__init__.py
mathsimplicity/mathsimplicity.py
mathsimplicity-1.1.3.dist-info/LICENSE
mathsimplicity-1.1.3.dist-info/METADATA
mathsimplicity-1.1.3.dist-info/WHEEL
mathsimplicity-1.1.3.dist-info/top_level.txt
mathsimplicity-1.1.3.dist-info/RECORD
