Metadata-Version: 2.1
Name: mathsimplicity
Version: 1.1.3
Summary: MathSimplicity is a Python package providing essential tools for basic mathematical computations, including prime factorization, range prime generation, fraction-to-decimal conversion, and GCD/LCM calculation.
Home-page: https://github.com/promoha90/mathsimplicity
Author: Mohamed Lotfi Hireche Benkert
Author-email: mohamedhireche74@gmail.com
License: MIT
Keywords: math,mathematics,education,prime numbers,factorization,fractions,decimals,GCD,LCM,arithmetic,basic math,learning,teaching,calculations
Classifier: License :: OSI Approved :: MIT License
Classifier: Operating System :: OS Independent
Classifier: Intended Audience :: Education
Classifier: Topic :: Education
Classifier: Topic :: Software Development :: Libraries :: Python Modules
Classifier: Programming Language :: Python :: 3
Classifier: Programming Language :: Python :: 3.6
Classifier: Programming Language :: Python :: 3.7
Classifier: Programming Language :: Python :: 3.8
Classifier: Programming Language :: Python :: 3.9
License-File: LICENSE
Requires-Dist: numexpr
